pip_services4_aws/__init__.py
pip_services4_aws/build/DefaultAwsFactory.py
pip_services4_aws/build/__init__.py
pip_services4_aws/clients/CommandableLambdaClient.py
pip_services4_aws/clients/LambdaClient.py
pip_services4_aws/clients/__init__.py
pip_services4_aws/connect/AwsConnectionParams.py
pip_services4_aws/connect/AwsConnectionResolver.py
pip_services4_aws/connect/__init__.py
pip_services4_aws/containers/CommandableLambdaFunction.py
pip_services4_aws/containers/LambdaFunction.py
pip_services4_aws/containers/__init__.py
pip_services4_aws/controllers/CommandableLambdaController.py
pip_services4_aws/controllers/ILambdaController.py
pip_services4_aws/controllers/LambdaAction.py
pip_services4_aws/controllers/LambdaController.py
pip_services4_aws/controllers/__init__.py
pip_services4_aws/count/CloudWatchCounters.py
pip_services4_aws/count/CloudWatchUnit.py
pip_services4_aws/count/__init__.py
pip_services4_aws/log/CloudWatchLogger.py
pip_services4_aws/log/__init__.py
pip_services4_aws/test/TestCommandableLambdaClient.py
pip_services4_aws/test/TestLambdaClient.py
pip_services4_aws/test/__init__.py
pip_services4_aws-0.0.1.dist-info/LICENSE
pip_services4_aws-0.0.1.dist-info/METADATA
pip_services4_aws-0.0.1.dist-info/WHEEL
pip_services4_aws-0.0.1.dist-info/top_level.txt
pip_services4_aws-0.0.1.dist-info/zip-safe
pip_services4_aws-0.0.1.dist-info/RECORD
